odoo/addons/stock_request/README.rst
odoo/addons/stock_request/__init__.py
odoo/addons/stock_request/__manifest__.py
odoo/addons/stock_request/data/stock_request_sequence_data.xml
odoo/addons/stock_request/i18n/ca.po
odoo/addons/stock_request/i18n/de.po
odoo/addons/stock_request/i18n/el_GR.po
odoo/addons/stock_request/i18n/es.po
odoo/addons/stock_request/i18n/es_ES.po
odoo/addons/stock_request/i18n/eu.po
odoo/addons/stock_request/i18n/fi.po
odoo/addons/stock_request/i18n/fr.po
odoo/addons/stock_request/i18n/fr_CH.po
odoo/addons/stock_request/i18n/fr_FR.po
odoo/addons/stock_request/i18n/gl.po
odoo/addons/stock_request/i18n/hr.po
odoo/addons/stock_request/i18n/hr_HR.po
odoo/addons/stock_request/i18n/it.po
odoo/addons/stock_request/i18n/ja.po
odoo/addons/stock_request/i18n/ja_JP.po
odoo/addons/stock_request/i18n/nl.po
odoo/addons/stock_request/i18n/nl_NL.po
odoo/addons/stock_request/i18n/pt.po
odoo/addons/stock_request/i18n/pt_BR.po
odoo/addons/stock_request/i18n/ro.po
odoo/addons/stock_request/i18n/ru.po
odoo/addons/stock_request/i18n/sl.po
odoo/addons/stock_request/i18n/stock_request.pot
odoo/addons/stock_request/i18n/tr.po
odoo/addons/stock_request/i18n/tr_TR.po
odoo/addons/stock_request/i18n/vi_VN.po
odoo/addons/stock_request/i18n/zh_CN.po
odoo/addons/stock_request/models/__init__.py
odoo/addons/stock_request/models/procurement_group.py
odoo/addons/stock_request/models/res_company.py
odoo/addons/stock_request/models/res_config_settings.py
odoo/addons/stock_request/models/stock_location.py
odoo/addons/stock_request/models/stock_move.py
odoo/addons/stock_request/models/stock_move_line.py
odoo/addons/stock_request/models/stock_picking.py
odoo/addons/stock_request/models/stock_request.py
odoo/addons/stock_request/models/stock_request_abstract.py
odoo/addons/stock_request/models/stock_request_allocation.py
odoo/addons/stock_request/models/stock_request_order.py
odoo/addons/stock_request/models/stock_route.py
odoo/addons/stock_request/models/stock_rule.py
odoo_addon_stock_request-18.0.1.1.3.1.dist-info/METADATA
odoo_addon_stock_request-18.0.1.1.3.1.dist-info/WHEEL
odoo_addon_stock_request-18.0.1.1.3.1.dist-info/top_level.txt
odoo_addon_stock_request-18.0.1.1.3.1.dist-info/RECORD
